eventsender/__init__.py
eventsender-1.2.2.dist-info/LICENSE
eventsender-1.2.2.dist-info/METADATA
eventsender-1.2.2.dist-info/WHEEL
eventsender-1.2.2.dist-info/top_level.txt
eventsender-1.2.2.dist-info/RECORD
