Metadata-Version: 2.1
Name: eventsender
Version: 1.2.2
Summary: RabbitMQ event sender
Home-page: https://github.com/ByteInternet/eventsender
Author: Byte B.V.
Author-email: tech@byte.nl
License: MIT License
Keywords: amqp rabbitmq events eventsender
Classifier: Development Status :: 5 - Production/Stable
Classifier: License :: OSI Approved :: MIT License
Classifier: Intended Audience :: Developers
Classifier: Topic :: Utilities
Classifier: Topic :: Communications
Classifier: Topic :: Internet
Classifier: Programming Language :: Python :: 2
Classifier: Programming Language :: Python :: 2.6
Classifier: Programming Language :: Python :: 2.7
Classifier: Programming Language :: Python :: 3
Classifier: Programming Language :: Python :: 3.5
Classifier: Programming Language :: Python :: 3.6
Classifier: Programming Language :: Python :: 3.7
License-File: LICENSE
Requires-Dist: pika ==1.3.2
